src/example_package_trder/__init__.py
src/example_package_trder/example.py
trder-0.0.1.dist-info/METADATA
trder-0.0.1.dist-info/WHEEL
trder-0.0.1.dist-info/licenses/LICENSE
trder-0.0.1.dist-info/RECORD
